supafunc/__init__.py
supafunc/_async/__init__.py
supafunc/_async/functions_client.py
supafunc/_sync/__init__.py
supafunc/_sync/functions_client.py
supafunc/errors.py
supafunc/utils.py
supafunc-0.5.0.dist-info/LICENSE
supafunc-0.5.0.dist-info/METADATA
supafunc-0.5.0.dist-info/WHEEL
supafunc-0.5.0.dist-info/RECORD
