Metadata-Version: 2.1
Name: supafunc
Version: 0.5.0
Summary: Library for Supabase Functions
Home-page: https://github.com/supabase-community/functions-py
License: MIT
Author: Joel Lee
Author-email: joel@joellee.org
Requires-Python: >=3.8,<4.0
Classifier: License :: OSI Approved :: MIT License
Classifier: Programming Language :: Python :: 3
Classifier: Programming Language :: Python :: 3.8
Classifier: Programming Language :: Python :: 3.9
Classifier: Programming Language :: Python :: 3.10
Classifier: Programming Language :: Python :: 3.11
Classifier: Programming Language :: Python :: 3.12
Requires-Dist: httpx[http2] (>=0.24,<0.28)
Project-URL: Repository, https://github.com/supabase-community/functions-py
